{
  "id": "codeium",
  "name": "Codeium",
  "description": "Free AI code completion and chat assistant with support for multiple programming languages",
  "category": "ai_development",
  "display_name": "Codeium",
  "version": "1.0.0",
  "last_updated": "2025-07-27T00:00:00Z",
  "status": "active",
  "is_active": true,
  "is_beta": false,
  "is_deprecated": false,
  "type": "ai",
  "source": "official",
  "priority": 60,
  "min_autopr_version": "0.1.0",
  "vendor": "Codeium",
  "website": "https://codeium.com",
  "pricing_model": "freemium",
  "supported_languages": [
    "python",
    "javascript",
    "typescript",
    "java",
    "c",
    "c++",
    "c#",
    "go",
    "rust",
    "ruby",
    "php",
    "swift",
    "kotlin",
    "dart",
    "elixir",
    "erlang",
    "haskell",
    "julia",
    "ocaml",
    "perl",
    "r",
    "scala",
    "sql",
    "bash",
    "powershell",
    "html",
    "css",
    "sass",
    "less"
  ],
  "tags": ["code_completion", "ai_assistant", "chat", "multi_language"],
  "documentation_url": "https://docs.codeium.com",
  "setup_guide": "https://docs.codeium.com/welcome/quickstart",
  "troubleshooting_guide": "https://docs.codeium.com/troubleshooting",
  "maintainer": "Codeium",

  "detection": {
    "files": [".codeium", "codeium.json", ".vscode/extensions.json"],
    "dependencies": ["codeium"],
    "folder_patterns": ["codeium", "-codeium"],
    "commit_patterns": ["codeium", "add codeium"],
    "content_patterns": ["codeium.com", "codeium config", "codeium:generate"],
    "confidence_weights": {
      "files": 0.5,
      "dependencies": 0.3,
      "folder_patterns": 0.1,
      "commit_patterns": 0.05,
      "content_patterns": 0.05
    }
  },

  "project_config": {
    "primary_language": "python",
    "framework": "codeium",
    "deployment_targets": ["local", "cloud"],
    "common_files": [".codeium/config.json", "codeium.json"],
    "features": [
      "ai_code_completion",
      "chat_interface",
      "context_aware_suggestions",
      "multi_language_support",
      "offline_mode"
    ],
    "configuration_files": [
      ".codeium/config.json",
      "codeium.json"
    ]
  }
}
